[
  {
    "name": "com.shanebeestudios.mcdeop.app.McDeobFxApp",
    "allDeclaredConstructors": true
  },
  {
    "name": "io.github.lxgaming.reconstruct.common.manager.TransformerManager",
    "allDeclaredFields": true
  },
  {
    "name": "io.github.lxgaming.reconstruct.common.transformer.minecraft.MinecraftTransformer",
    "allDeclaredConstructors": true
  },
  {
    "name": "io.github.lxgaming.reconstruct.common.transformer.proguard.ProGuardTransformer",
    "allDeclaredConstructors": true
  },
  {
    "name": "io.github.lxgaming.reconstruct.common.transformer.rename.RenameTransformer",
    "allDeclaredConstructors": true
  }
]
